ashrae/__init__.py
ashrae/_nbdev.py
ashrae/feature_testing.py
ashrae/inspection.py
ashrae/leaderboard.py
ashrae/loading.py
ashrae/modelling.py
ashrae/preprocessing.py
ashrae-0.0.1.dist-info/LICENSE
ashrae-0.0.1.dist-info/METADATA
ashrae-0.0.1.dist-info/WHEEL
ashrae-0.0.1.dist-info/entry_points.txt
ashrae-0.0.1.dist-info/top_level.txt
ashrae-0.0.1.dist-info/RECORD
