Metadata-Version: 2.1
Name: ashrae
Version: 0.0.1
Summary: This project contains inspection and pre-processing tools to build machine learning models for the ASHRAE - Great Energy Predictor III challenge on kaggle.
Home-page: https://github.com/eschmidt42/ashrae/tree/master/
Author: Eric Schmidt
Author-email: wuppening@gmail.com
License: Apache Software License 2.0
Keywords: fastai scikit-learn kaggle ashrae
Platform: UNKNOWN
Classifier: Development Status :: 3 - Alpha
Classifier: Intended Audience :: Developers
Classifier: License :: OSI Approved :: Apache Software License
Classifier: Natural Language :: English
Classifier: Programming Language :: Python :: 3.8
Requires-Python: >=3.8
